Metadata-Version: 2.1
Name: enveasy
Version: 1.0.0
Summary: Easy-to-use functionality for managing files in different environments
Home-page: UNKNOWN
Author: Antoine PINTO
Author-email: antoine.pinto1@outlook.fr
License: MIT
Platform: UNKNOWN
License-File: LICENSE
